atlantisfastapi/__init__.py
atlantisfastapi/lib/__init__.py
atlantisfastapi/lib/security/__init__.py
atlantisfastapi/lib/security/http.py
atlantisfastapi-9.0.0.dist-info/METADATA
atlantisfastapi-9.0.0.dist-info/WHEEL
atlantisfastapi-9.0.0.dist-info/top_level.txt
atlantisfastapi-9.0.0.dist-info/RECORD
