Metadata-Version: 2.4
Name: atlantisfastapi
Version: 9.0.0
Summary: atlantisfastapi
Author-email: Atlantis Labs <r00tail@protonmail.com>
Requires-Dist: coderfastapi~=6.0.0
Requires-Dist: atlantiscore~=12.0
Provides-Extra: test
Requires-Dist: pytest~=7.4; extra == "test"
Requires-Dist: pytest-asyncio~=0.21; extra == "test"
Requires-Dist: pytest-cov~=4.1; extra == "test"
Requires-Dist: pytest-mock~=3.11; extra == "test"
Requires-Dist: pytest-xdist[psutil]~=3.3; extra == "test"
Provides-Extra: dev
Requires-Dist: black~=23.9; extra == "dev"
